textar/ES_stopwords.txt
textar/__init__.py
textar/text_classifier.py
textar-0.0.6.dist-info/DESCRIPTION.rst
textar-0.0.6.dist-info/METADATA
textar-0.0.6.dist-info/RECORD
textar-0.0.6.dist-info/WHEEL
textar-0.0.6.dist-info/metadata.json
textar-0.0.6.dist-info/top_level.txt
