Metadata-Version: 2.0
Name: textar
Version: 0.0.6
Summary: Paquete en python para análisis, clasificación y recuperación de textos, utilizado por el equipo de Datos Argentina.
Home-page: https://github.com/datosgobar/textar
Author: Datos Argentina
Author-email: datos@modernizacion.gob.ar
License: MIT license
Keywords: textar
Platform: UNKNOWN
Classifier: Development Status :: 2 - Pre-Alpha
Classifier: Intended Audience :: Developers
Classifier: License :: OSI Approved :: MIT License
Classifier: Natural Language :: Spanish
Classifier: Programming Language :: Python :: 2
Classifier: Programming Language :: Python :: 2.7
Requires-Dist: numpy
Requires-Dist: pandas
Requires-Dist: scikit-learn
Requires-Dist: scipy
